{"nodes": [{"id": "backend_src_middlewares_cache_middleware_ts", "label": "cache.middleware.ts", "file_type": "code", "source_file": "backend\\src\\middlewares\\cache.middleware.ts", "source_location": "L1"}, {"id": "cache_middleware_buildkey", "label": "buildKey()", "file_type": "code", "source_file": "backend\\src\\middlewares\\cache.middleware.ts", "source_location": "L10"}, {"id": "cache_middleware_cacheresponse", "label": "cacheResponse()", "file_type": "code", "source_file": "backend\\src\\middlewares\\cache.middleware.ts", "source_location": "L24"}, {"id": "cache_middleware_invalidatecache", "label": "invalidateCache()", "file_type": "code", "source_file": "backend\\src\\middlewares\\cache.middleware.ts", "source_location": "L64"}], "edges": [{"source": "backend_src_middlewares_cache_middleware_ts", "target": "express", "relation": "imports_from", "confidence": "EXTRACTED", "source_file": "backend\\src\\middlewares\\cache.middleware.ts", "source_location": "L1", "weight": 1.0}, {"source": "backend_src_middlewares_cache_middleware_ts", "target": "backend_src_utils_redis_util", "relation": "imports_from", "confidence": "EXTRACTED", "source_file": "backend\\src\\middlewares\\cache.middleware.ts", "source_location": "L2", "weight": 1.0}, {"source": "backend_src_middlewares_cache_middleware_ts", "target": "cache_middleware_buildkey", "relation": "contains", "confidence": "EXTRACTED", "source_file": "backend\\src\\middlewares\\cache.middleware.ts", "source_location": "L10", "weight": 1.0}, {"source": "backend_src_middlewares_cache_middleware_ts", "target": "cache_middleware_cacheresponse", "relation": "contains", "confidence": "EXTRACTED", "source_file": "backend\\src\\middlewares\\cache.middleware.ts", "source_location": "L24", "weight": 1.0}, {"source": "backend_src_middlewares_cache_middleware_ts", "target": "cache_middleware_invalidatecache", "relation": "contains", "confidence": "EXTRACTED", "source_file": "backend\\src\\middlewares\\cache.middleware.ts", "source_location": "L64", "weight": 1.0}], "raw_calls": [{"caller_nid": "cache_middleware_buildkey", "callee": "toString", "source_file": "backend\\src\\middlewares\\cache.middleware.ts", "source_location": "L11"}, {"caller_nid": "cache_middleware_invalidatecache", "callee": "delPattern", "source_file": "backend\\src\\middlewares\\cache.middleware.ts", "source_location": "L67"}]}